quacknet/__init__.py
quacknet/CNN/__init__.py
quacknet/CNN/manager.py
quacknet/CNN/layers/__init__.py
quacknet/CNN/layers/activationLayer.py
quacknet/CNN/layers/conv1DLayer.py
quacknet/CNN/layers/conv2DLayer.py
quacknet/CNN/layers/denseLayer.py
quacknet/CNN/layers/globalAveragePoolingLayer.py
quacknet/CNN/layers/poolingLayer.py
quacknet/NN/NNManager.py
quacknet/NN/__init__.py
quacknet/NN/backPropgation.py
quacknet/NN/initialisers.py
quacknet/NN/writeAndReadWeightBias.py
quacknet/RNN/__init__.py
quacknet/RNN/Singular/SingularBackPropRNN.py
quacknet/RNN/Singular/SingularRNN.py
quacknet/RNN/Singular/__init__.py
quacknet/RNN/Stacked/StackedBackPropRNN.py
quacknet/RNN/Stacked/StackedRNN.py
quacknet/RNN/Stacked/__init__.py
quacknet/Transformer/BaseTransformerClasses.py
quacknet/Transformer/ManagerTransformer.py
quacknet/Transformer/__init__.py
quacknet/Transformer/layers/AttentionBackpropagation.py
quacknet/Transformer/layers/EmbeddingLayer.py
quacknet/Transformer/layers/FeedForwardNetwork.py
quacknet/Transformer/layers/LinearLayer.py
quacknet/Transformer/layers/MultiHeadAttention.py
quacknet/Transformer/layers/NormLayer.py
quacknet/Transformer/layers/PositionalEncoding.py
quacknet/Transformer/layers/ResidualConnection.py
quacknet/Transformer/layers/__init__.py
quacknet/core/__init__.py
quacknet/core/activations/__init__.py
quacknet/core/activations/activationDerivativeFunctions.py
quacknet/core/activations/activationFunctions.py
quacknet/core/losses/__init__.py
quacknet/core/losses/lossDerivativeFunctions.py
quacknet/core/losses/lossFunctions.py
quacknet/core/optimisers/__init__.py
quacknet/core/optimisers/adam.py
quacknet/core/optimisers/gradientDescent.py
quacknet/core/optimisers/stochasticGD.py
quacknet/core/utilities/__init__.py
quacknet/core/utilities/checker.py
quacknet/core/utilities/dataAugmentation.py
quacknet/core/utilities/drawGraphs.py
quacknet-1.6.dist-info/licenses/LICENSE
quacknet-1.6.dist-info/METADATA
quacknet-1.6.dist-info/WHEEL
quacknet-1.6.dist-info/top_level.txt
quacknet-1.6.dist-info/RECORD
